tws_drex_mcp/__about__.py
tws_drex_mcp/__init__.py
tws_drex_mcp/__main__.py
tws_drex_mcp/cli.py
tws_drex_mcp/server.py
tws_drex_mcp-0.1.20250710.225741.dist-info/METADATA
tws_drex_mcp-0.1.20250710.225741.dist-info/WHEEL
tws_drex_mcp-0.1.20250710.225741.dist-info/entry_points.txt
tws_drex_mcp-0.1.20250710.225741.dist-info/licenses/LICENSE
tws_drex_mcp-0.1.20250710.225741.dist-info/RECORD
