Metadata-Version: 2.4
Name: tws-drex-mcp
Version: 0.1.20250710.225741
Summary: An MCP server providing tools to interact with the DREX document extraction AI API via LoginRadius authentication.
Project-URL: Homepage, https://github.com/thoughtswinsystems/drex-api
Author-email: chris-tws <christopher.lin@thoughtswinsystems.com>
License-File: LICENSE
Classifier: Development Status :: 3 - Alpha
Classifier: Intended Audience :: Developers
Classifier: Programming Language :: Python :: 3
Classifier: Programming Language :: Python :: 3.12
Classifier: Topic :: Software Development :: Libraries :: Python Modules
Requires-Python: >=3.12
Requires-Dist: aiofiles>=24.1.0
Requires-Dist: loginradius-v2>=11.7.0
Requires-Dist: mcp[cli]>=1.7.0
